README.md
pyproject.toml
requirements.txt
setup.py
./genesis_bots/__init__.py
./genesis_bots/api/LICENSE
./genesis_bots/api/README.md
./genesis_bots/api/__init__.py
./genesis_bots/api/genesis_api.py
./genesis_bots/api/genesis_base.py
./genesis_bots/api/server_proxy.py
./genesis_bots/api/utils.py
./genesis_bots/apps/__init__.py
./genesis_bots/apps/cli.py
./genesis_bots/apps/install_resources.py
./genesis_bots/apps/genesis-voice/LICENSE
./genesis_bots/apps/genesis-voice/README.md
./genesis_bots/apps/genesis-voice/package.json
./genesis_bots/apps/genesis-voice/tsconfig.json
./genesis_bots/apps/genesis_server/__init__.py
./genesis_bots/apps/genesis_server/bot_os_multibot_1.py
./genesis_bots/apps/genesis_server/deployments/snowflake_app/Dev_build_and_test_process.md
./genesis_bots/apps/genesis_server/deployments/snowflake_app/call_copilot_api.py
./genesis_bots/apps/genesis_server/deployments/snowflake_app/copy_shared_harvest.py
./genesis_bots/apps/genesis_server/deployments/snowflake_app/genesis_account_setup.sql
./genesis_bots/apps/genesis_server/deployments/snowflake_app/genesis_spcs_test.sql
./genesis_bots/apps/genesis_server/deployments/snowflake_app/image_upload.py
./genesis_bots/apps/genesis_server/deployments/snowflake_app/log_replication_setup.sql
./genesis_bots/apps/genesis_server/deployments/snowflake_app/readme.md
./genesis_bots/apps/genesis_server/deployments/snowflake_app/setup_script.sql
./genesis_bots/apps/genesis_server/deployments/snowflake_app/backup/backup_metadata.sql
./genesis_bots/apps/genesis_server/deployments/snowflake_app/backup/restore_metadata.sql
./genesis_bots/apps/streamlit_gui/Genesis-Computing-Logo-Black.png
./genesis_bots/apps/streamlit_gui/Genesis-Computing-Logo-White.png
./genesis_bots/apps/streamlit_gui/Genesis-Computing-Logo-White.webp
./genesis_bots/apps/streamlit_gui/Genesis.py
./genesis_bots/apps/streamlit_gui/__init__.py
./genesis_bots/apps/streamlit_gui/environment.yml
./genesis_bots/apps/streamlit_gui/make_alpha_sis_launch.py
genesis_bots.egg-info/PKG-INFO
genesis_bots.egg-info/SOURCES.txt
genesis_bots.egg-info/dependency_links.txt
genesis_bots.egg-info/entry_points.txt
genesis_bots.egg-info/not-zip-safe
genesis_bots.egg-info/requires.txt
genesis_bots.egg-info/top_level.txt
