Metadata-Version: 2.4
Name: genesis_bots
Version: 1.0.51
Summary: Genesis Bots Package
Author-email: Justin Langseth <justin.langseth@genesiscomputing.ai>, Michael Rainey <michael.rainey@genesiscomputing.ai>
License: SSPL
Project-URL: Documentation, https://docs.genesiscomputing.com/docs/home
Project-URL: Homepage, https://genesiscomputing.ai
Project-URL: Repository, https://github.com/genesis-bots/genesis-bots/
Classifier: Programming Language :: Python :: 3
Classifier: License :: Other/Proprietary License
Classifier: Operating System :: OS Independent
Requires-Python: >=3.10
Requires-Dist: annoy==1.17.3
Requires-Dist: Brotli==1.0.9
Requires-Dist: APscheduler
Requires-Dist: bs4
Requires-Dist: db-dtypes
Requires-Dist: dill
Requires-Dist: protobuf==4.21.11
Requires-Dist: google-api-python-client
Requires-Dist: google-auth-httplib2
Requires-Dist: google-auth-oauthlib
Requires-Dist: werkzeug>=3.0.6
Requires-Dist: flask==3.0.3
Requires-Dist: google-cloud-bigquery
Requires-Dist: mistralai
Requires-Dist: openai>=1.66.0
Requires-Dist: pandas==2.1.4
Requires-Dist: pyarrow==17.0.0
Requires-Dist: pytest
Requires-Dist: flask-cors==5.0.1
Requires-Dist: pyyaml==6.0.1
Requires-Dist: simplejson==3.19.2
Requires-Dist: slack_bolt
Requires-Dist: streamlit==1.35.0
Requires-Dist: streamlit_autorefresh
Requires-Dist: urllib3==1.26.19
Requires-Dist: ngrok
Requires-Dist: snowflake_connector_python==3.12.3
Requires-Dist: reka-api
Requires-Dist: google-generativeai
Requires-Dist: pdb_attach
Requires-Dist: sseclient
Requires-Dist: botbuilder-integration-aiohttp>=4.15.0
Requires-Dist: jira==3.8.0
Requires-Dist: gitpython==3.1.43
Requires-Dist: anthropic==0.40.0
Requires-Dist: boto3>=1.26.0
Requires-Dist: markdown
Requires-Dist: cython
Requires-Dist: tenacity
Requires-Dist: dagster==1.9.5
Requires-Dist: dagster-graphql
Requires-Dist: dagster-spark
Requires-Dist: dagster-dbt
Requires-Dist: wrapt
Requires-Dist: sqlalchemy>=1.4.0
Requires-Dist: psycopg2-binary==2.9.9
Requires-Dist: pymysql
Requires-Dist: snowflake-sqlalchemy
Requires-Dist: spider-client
Requires-Dist: openpyxl
Requires-Dist: sqlalchemy-redshift
Requires-Dist: sqlalchemy-bigquery
Requires-Dist: PyGithub
Requires-Dist: sqlalchemy-databricks
Requires-Dist: dbt-core
Requires-Dist: dbt-snowflake
Requires-Dist: pymupdf
Requires-Dist: jsonpickle
Requires-Dist: jmespath
Requires-Dist: llama-index
Requires-Dist: pypdf
Requires-Dist: sentence-transformers
Requires-Dist: xlrd
Requires-Dist: fastapi==0.115.11
Requires-Dist: chromadb
Requires-Dist: llama-index[chromadb]
Requires-Dist: llama-index-vector-stores-chroma
